{
  "title": "The Suppressive and Emergent Phenomenon: H as a Control Surface",
  "description": "<p>Live streaming and VTuber communities constitute the largest naturally occurring laboratory for parasocial &kappa;-dynamics currently observable. Tens of millions of viewers form high-coupling bonds with performers they have never met; for many, these relationships constitute the primary vector through which healthy-state representations enter their generative model for the first time. The MBD framework &mdash; which models personality as a state-space system updated by lived experience &mdash; predicts this outcome precisely: high-&kappa; social inputs from a trusted source can expand H<sub>agent</sub> into previously unrepresented state space regardless of whether the relationship is co-present. The phenomenon is not parasocial pathology. It is the Re-zeroing Protocol running at scale, mediated by broadcasting infrastructure instead of physical proximity.</p><p>Paper 7 of the Memory as Baseline Deviation series established the endemic baseline as a naturally occurring calibration failure: B(0) constructed during chronic disruption, with the Horizon H = H<sub>accessible</sub> \\ H<sub>agent</sub> denoting states that are neurobiologically reachable but absent from the agent&rsquo;s generative model. That paper treated this condition as arising from circumstance. This paper examines a harder claim: the same calibration failure can be produced deliberately. An agent &mdash; platform, institution, abuser &mdash; that controls which states a population occupies can engineer H over time. The mathematics do not distinguish between endemic baseline arising from circumstance and endemic baseline arising from design.</p><p>Four attack vectors are formalized with their population-level signatures and detection criteria. V1 (<em>Isolation from Knowledge</em>) suppresses informational inputs that would enable H<sub>agent</sub> expansion. V2 (<em>Episodic Erasure</em>) degrades or falsifies the episodic record. V3 (<em>Coupling Collapse</em>) drives the social coupling coefficient &kappa; below the critical threshold at which therapeutic relationships can form. V4 (<em>Re-zeroing Suppression</em>) targets the corrective mechanism directly. All four are observable in the parasocial economy: deplatforming, algorithmic isolation, community weaponization, and content suppression each instantiate a vector.</p><p>A critical coupling threshold &kappa;<sub>c</sub> is derived by analogy with the Kuramoto synchronization threshold: below &kappa;<sub>c</sub>, collective re-zeroing fails; above it, high-&kappa; fandom communities can expand each other&rsquo;s H<sub>agent</sub> faster than the suppressive mechanism can contract it. This is a testable, falsifiable prediction with computational labs provided in the repository.</p>",
  "creators": [
    {
      "name": "Everett, Brandon",
      "orcid": "0009-0007-6676-4897"
    }
  ],
  "keywords": [
    "memory as baseline deviation",
    "adversarial horizon engineering",
    "endemic baseline",
    "kappa coupling",
    "recursive immunity",
    "tamper evidence",
    "computational social science",
    "episodic erasure",
    "re-zeroing protocol",
    "Lenia property",
    "parasocial dynamics",
    "VTuber",
    "streaming culture",
    "fandom",
    "platform dynamics"
  ],
  "license": "Apache-2.0",
  "upload_type": "software",
  "access_right": "open",
  "related_identifiers": [
    {
      "identifier": "https://doi.org/10.5281/zenodo.18652919",
      "relation": "isDerivedFrom",
      "scheme": "doi"
    },
    {
      "identifier": "https://github.com/YellowHapax/MBD-Framework",
      "relation": "isDerivedFrom",
      "scheme": "url"
    },
    {
      "identifier": "https://github.com/YellowHapax/Endemic-Baseline",
      "relation": "isDerivedFrom",
      "scheme": "url"
    }
  ]
}
